Metadata-Version: 2.1
Name: ALS.Liam
Version: 0.9.0
Summary: Visualize CCD data from ALS BL 4.0.2 diffractometer
Home-page: https://bitbucket.org/berkeleylab/als.liam/src/master/
Author: Padraic Shafer
Author-email: pshafer@lbl.gov
License: UNKNOWN
Keywords: CCD RSXD x-ray ALS BL4.0.2 diffraction
Platform: UNKNOWN
Classifier: Development Status :: 4 - Beta
Classifier: Intended Audience :: Science/Research
Classifier: Topic :: Scientific/Engineering :: Physics
Classifier: License :: OSI Approved :: BSD License
Classifier: Programming Language :: Python :: 2
Classifier: Programming Language :: Python :: 2.7
Classifier: Operating System :: OS Independent
Classifier: Environment :: Console
